s1290005_learn/__init__.py
s1290005_learn/main.py
s1290005_learn/statistics/__init__.py
s1290005_learn/statistics/frequenciesOfItems.py
s1290005_learn/visualization/__init__.py
s1290005_learn/visualization/heatMapItemsFrequencies.py
s1290005_learn-0.0.1.dist-info/METADATA
s1290005_learn-0.0.1.dist-info/WHEEL
s1290005_learn-0.0.1.dist-info/top_level.txt
s1290005_learn-0.0.1.dist-info/RECORD
