Metadata-Version: 2.1
Name: s1290005-learn
Version: 0.0.1
Summary: heat map pm25
Home-page: https://github.com/s1290005/s1290005_learn
Author: s1290005
Author-email: s1290005@u-aizu.ac.jp
Classifier: Programming Language :: Python :: 3.7
Classifier: License :: OSI Approved :: MIT License
Classifier: Operating System :: OS Independent
